{
	"variables": [],
	"info": {
		"name": "sample-api",
		"_postman_id": "5b0438e2-a181-ecb2-ab4a-727c4082d73d",
		"description": "",
		"schema": "https://schema.getpostman.com/json/collection/v2.0.0/collection.json"
	},
	"item": [
		{
			"name": "Create User",
			"request": {
				"url": "localhost:4000/users",
				"method": "POST",
				"header": [
					{
						"key": "Content-Type",
						"value": "application/json",
						"description": ""
					}
				],
				"body": {
					"mode": "raw",
					"raw": "{\n\t\"name\": \"Tech Prastish\",\n\t\"email\":\"officialtpss@gmail.com\",\n\t\"password\": \"123456789\"\n}"
				},
				"description": ""
			},
			"response": []
		},
		{
			"name": "Login User",
			"request": {
				"url": "localhost:4000/users",
				"method": "PUT",
				"header": [
					{
						"key": "Content-Type",
						"value": "application/json",
						"description": ""
					}
				],
				"body": {
					"mode": "raw",
					"raw": "{\n\t\"email\":\"officialtpss@gmail.com\",\n\t\"password\": \"123456789\"\n}"
				},
				"description": ""
			},
			"response": []
		},
		{
			"name": "Update User",
			"request": {
				"url": "localhost:4000/user/profile",
				"method": "PUT",
				"header": [
					{
						"key": "Content-Type",
						"value": "application/x-www-form-urlencoded",
						"description": "",
						"disabled": true
					},
					{
						"key": "Authorization",
						"value": "Bearer eyJhbGciOiJIUzI1NiIsInR5cCI6IkpXVCJ9.eyJ1c2VySWQiOiI1ZWRhMTE3MjlkYzE5YzZmZWRiY2QyODgiLCJpYXQiOjE1OTEzNTA4MjJ9.AMPl4qOUsR61Tggu_lWrIMtBoFBQp7woTIpNsDLbUPY",
						"description": ""
					}
				],
				"body": {
					"mode": "formdata",
					"formdata": [
						{
							"key": "file",
							"description": "",
							"type": "file",
							"src": "Companies_108586_CompanyLogoURL.jpeg"
						}
					]
				},
				"description": ""
			},
			"response": []
		}
	]
}